Workbook

Sheet Employee Data
A1: Unreal Consulting — Employee Dataset (Solved Workbook)
A2: Employee ID | B2: Full Name | C2: Department | D2: Job Level | E2: Location | F2: Work Mode | G2: Gender | H2: Age | I2: Tenure (Years) | J2: Salary (£) | K2: Bonus % | L2: Performance Rating | M2: Training Hours | N2: Last Promotion | O2: Voluntary Leaver | P2: Manager ID
A3: UC-0001 | B3: Emre Tessema | C3: Technology | D3: Director | E3: London | F3: Hybrid | G3: Male | H3: 50 | I3: 7.1 | J3: 149500 | K3: 21.2 | L3: 3 | M3: 22 | N3: 2022 | O3: No | P3: UC-0000
A4: UC-0002 | B4: Indigo Turner | C4: Technology | D4: Director | E4: London | F4: Hybrid | G4: Non-binary | H4: 49 | I4: 11.5 | J4: 137000 | K4: 19.2 | L4: 3 | M4: 13 | N4: 2021 | O4: No | P4: UC-0000
A5: UC-0003 | B5: Fatima Cross | C5: Technology | D5: Director | E5: London | F5: Office | G5: Female | H5: 42 | I5: 11.2 | J5: 139500 | K5: 21.4 | L5: 3 | M5: 15 | N5: 2024 | O5: No | P5: UC-0000
A6: UC-0004 | B6: Elspeth Campbell | C6: Technology | D6: Lead | E6: London | F6: Hybrid | G6: Female | H6: 30 | I6: 9.4 | J6: 102000 | K6: 18.6 | L6: 3 | M6: 14 | N6: 2020 | O6: No | P6: UC-0001
A7: UC-0005 | B7: Brigitte Vargas | C7: Technology | D7: Lead | E7: Edinburgh | F7: Hybrid | G7: Female | H7: 42 | I7: 5.3 | J7: 104500 | K7: 16.2 | L7: 4 | M7: 22 | N7: 2021 | O7: Yes | P7: UC-0001
A8: UC-0006 | B8: Michael Finlay | C8: Technology | D8: Lead | E8: London | F8: Office | G8: Male | H8: 35 | I8: 7.6 | J8: 108500 | K8: 14.9 | L8: 3 | M8: 18 | N8: 2023 | O8: No | P8: UC-0001
A9: UC-0007 | B9: Victor Ahmed | C9: Technology | D9: Lead | E9: London | F9: Hybrid | G9: Male | H9: 42 | I9: 8.8 | J9: 123500 | K9: 18.6 | L9: 4 | M9: 16 | N9: 2023 | O9: No | P9: UC-0001
A10: UC-0008 | B10: Yusuf Bradley | C10: Technology | D10: Lead | E10: London | F10: Remote | G10: Male | H10: 29 | I10: 6 | J10: 123000 | K10: 19.1 | L10: 5 | M10: 17 | N10: 2024 | O10: No | P10: UC-0001
A11: UC-0009 | B11: Cian Osei | C11: Technology | D11: Lead | E11: London | F11: Office | G11: Male | H11: 36 | I11: 9.6 | J11: 117500 | K11: 18.1 | L11: 4 | M11: 18 | N11: 2023 | O11: No | P11: UC-0001
A12: UC-0010 | B12: Fatima Bergstrom | C12: Technology | D12: Lead | E12: London | F12: Hybrid | G12: Female | H12: 42 | I12: 6.9 | J12: 111000 | K12: 19.5 | L12: 5 | M12: 15 | N12: 2022 | O12: No | P12: UC-0001
A13: UC-0011 | B13: Chioma Ahmed | C13: Technology | D13: Senior | E13: London | F13: Remote | G13: Female | H13: 36 | I13: 6.5 | J13: 90000 | K13: 13.8 | L13: 5 | M13: 34 | N13: 2021 | O13: Yes | P13: UC-0004
A14: UC-0012 | B14: Hugo Dubois | C14: Technology | D14: Senior | E14: London | F14: Hybrid | G14: Male | H14: 34 | I14: 7.1 | J14: 83500 | K14: 14.6 | L14: 3 | M14: 23 | N14: 2021 | O14: No | P14: UC-0004
... A40: UC-0038 | B40: Andrei Tessema | C40: Technology | D40: Mid | E40: London | F40: Remote | G40: Male | H40: 25 | I40: 2.3 | J40: 56500 | K40: 8.6 | L40: 3 | M40: 25 | N40: 2024 | O40: No | P40: UC-0011
A41: UC-0039 | B41: Bence Al-Hassan | C41: Technology | D41: Junior | E41: London | F41: Hybrid | G41: Male | H41: 27 | I41: 2 | J41: 41500 | K41: 7.4 | L41: 4 | M41: 45 | O41: Yes | P41: UC-0023
A42: UC-0040 | B42: Anna Nkosi | C42: Technology | D42: Junior | E42: London | F42: Hybrid | G42: Female | H42: 23 | I42: 2.7 | J42: 40500 | K42: 5.1 | L42: 4 | M42: 44 | O42: Yes | P42: UC-0023
A43: UC-0041 | B43: Lena Rao | C43: Technology | D43: Junior | E43: London | F43: Remote | G43: Female | H43: 24 | I43: 1.2 | J43: 30000 | K43: 2.7 | L43: 2 | M43: 28 | O43: No | P43: UC-0023
A44: UC-0042 | B44: Elena Lin | C44: Technology | D44: Junior | E44: London | F44: Remote | G44: Female | H44: 24 | I44: 2.2 | J44: 35000 | K44: 6 | L44: 3 | M44: 27 | O44: No | P44: UC-0023
A45: UC-0043 | B45: Tunde Alderton | C45: Technology | D45: Junior | E45: London | F45: Hybrid | G45: Male | H45: 22 | I45: 1.8 | J45: 43000 | K45: 5.2 | L45: 4 | M45: 38 | N45: 2023 | O45: Yes | P45: UC-0023
A46: UC-0044 | B46: Olamide Bergstrom | C46: Technology | D46: Junior | E46: Manchester | F46: Office | G46: Female | H46: 24 | I46: 1.3 | J46: 36500 | K46: 8.4 | L46: 4 | M46: 30 | O46: Yes | P46: UC-0023
A47: UC-0045 | B47: Rosalyn Mansouri | C47: Technology | D47: Junior | E47: Manchester | F47: Remote | G47: Female | H47: 22 | I47: 0.3 | J47: 34500 | K47: 2.6 | L47: 3 | M47: 36 | O47: No | P47: UC-0023
A48: UC-0046 | B48: Raphael Ojo | C48: Technology | D48: Junior | E48: Manchester | F48: Hybrid | G48: Male | H48: 23 | I48: 0.3 | J48: 35000 | K48: 4.8 | L48: 3 | M48: 34 | O48: No | P48: UC-0023
A49: UC-0047 | B49: Raphael Reynolds | C49: Technology | D49: Junior | E49: London | F49: Remote | G49: Male | H49: 23 | I49: 2.6 | J49: 40000 | K49: 2.5 | L49: 3 | M49: 30 | N49: 2023 | O49: No | P49: UC-0023
A50: UC-0048 | B50: Niall Dubois | C50: Technology | D50: Junior | E50: London | F50: Hybrid | G50: Male | H50: 24 | I50: 0.3 | J50: 42000 | K50: 5.3 | L50: 4 | M50: 45 | O50: No | P50: UC-0023
A51: UC-0049 | B51: Connor Evans | C51: Technology | D51: Junior | E51: London | F51: Hybrid | G51: Male | H51: 24 | I51: 2.2 | J51: 42500 | K51: 6.8 | L51: 4 | M51: 26 | N51: 2022 | O51: Yes | P51: UC-0023
A52: UC-0050 | B52: Helene Reid | C52: Technology | D52: Junior | E52: London | F52: Office | G52: Female | H52: 27 | I52: 2.5 | J52: 38500 | K52: 6.5 | L52: 4 | M52: 33 | O52: No | P52: UC-0023
A53: UC-0051 | B53: Darius Mensah | C53: Strategy | D53: Director | E53: Edinburgh | F53: Hybrid | G53: Male | H53: 49 | I53: 9.9 | J53: 145500 | K53: 20.4 | L53: 3 | M53: 9 | N53: 2024 | O53: No | P53: UC-0000
A54: UC-0052 | B54: Layla Hassan | C54: Strategy | D54: Director | E54: Edinburgh | F54: Office | G54: Female | H54: 48 | I54: 10 | J54: 144000 | K54: 20.1 | L54: 4 | M54: 13 | N54: 2021 | O54: No | P54: UC-0000
A55: UC-0053 | B55: Zoe Okafor | C55: Strategy | D55: Lead | E55: Edinburgh | F55: Hybrid | G55: Female | H55: 42 | I55: 8.5 | J55: 99500 | K55: 17 | L55: 3 | M55: 8 | N55: 2020 | O55: No | P55: UC-0051
A56: UC-0054 | B56: Nathan Wright | C56: Strategy | D56: Lead | E56: London | F56: Office | G56: Male | H56: 43 | I56: 8 | J56: 115000 | K56: 18.7 | L56: 4 | M56: 4 | N56: 2022 | O56: No | P56: UC-0051
A57: UC-0055 | B57: Cecilia Mansouri | C57: Strategy | D57: Lead | E57: Manchester | F57: Hybrid | G57: Female | H57: 41 | I57: 11.5 | J57: 94500 | K57: 16.7 | L57: 3 | M57: 19 | N57: 2023 | O57: No | P57: UC-0051
A58: UC-0056 | B58: Seun Draper | C58: Strategy | D58: Lead | E58: London | F58: Remote | G58: Male | H58: 36 | I58: 7.7 | J58: 113500 | K58: 18.4 | L58: 4 | M58: 12 | N58: 2023 | O58: No | P58: UC-0051
A59: UC-0057 | B59: Rebecca MacDonald | C59: Strategy | D59: Lead | E59: London | F59: Office | G59: Female | H59: 48 | I59: 12.4 | J59: 94000 | K59: 12.9 | L59: 2 | M59: 14 | N59: 2021 | O59: No | P59: UC-0051
A60: UC-0058 | B60: Abdou Nwosu | C60: Strategy | D60: Senior | E60: London | F60: Hybrid | G60: Male | H60: 35 | I60: 7.8 | J60: 86000 | K60: 11.6 | L60: 3 | M60: 7 | N60: 2022 | O60: No | P60: UC-0053
A61: UC-0059 | B61: Sasha Anand | C61: Strategy | D61: Senior | E61: Edinburgh | F61: Hybrid | G61: Non-binary | H61: 34 | I61: 7.9 | J61: 88000 | K61: 12.7 | L61: 4 | M61: 17 | N61: 2023 | O61: No | P61: UC-0053
A62: UC-0060 | B62: Hamid Santos | C62: Strategy | D62: Senior | E62: London | F62: Remote | G62: Male | H62: 27 | I62: 6 | J62: 79000 | K62: 11.6 | L62: 3 | M62: 8 | N62: 2023 | O62: No | P62: UC-0053
A63: UC-0061 | B63: Isabel Vargas | C63: Strategy | D63: Senior | E63: London | F63: Hybrid | G63: Female | H63: 25 | I63: 0.9 | J63: 62500 | K63: 7.3 | L63: 2 | M63: 8 | N63: 2024 | O63: No | P63: UC-0053
A64: UC-0062 | B64: Adebayo Ojo | C64: Strategy | D64: Senior | E64: Manchester | F64: Hybrid | G64: Male | H64: 36 | I64: 2.8 | J64: 77500 | K64: 10.3 | L64: 3 | M64: 18 | N64: 2023 | O64: No | P64: UC-0053
... A82: UC-0080 | B82: Natalie Eriksson | C82: Strategy | D82: Mid | E82: London | F82: Remote | G82: Female | H82: 32 | I82: 2.1 | J82: 48000 | K82: 6.2 | L82: 3 | M82: 28 | N82: 2024 | O82: No | P82: UC-0058
A83: UC-0081 | B83: Arjun Nakamura | C83: Strategy | D83: Junior | E83: London | F83: Remote | G83: Male | H83: 24 | I83: 1.9 | J83: 31500 | K83: 3.2 | L83: 1 | M83: 28 | O83: No | P83: UC-0068
A84: UC-0082 | B84: Jae-won Holloway | C84: Strategy | D84: Junior | E84: London | F84: Office | G84: Male | H84: 23 | I84: 0.3 | J84: 33500 | K84: 4.5 | L84: 3 | M84: 30 | O84: No | P84: UC-0068
A85: UC-0083 | B85: Freya Sato | C85: Strategy | D85: Junior | E85: Manchester | F85: Hybrid | G85: Female | H85: 27 | I85: 1.2 | J85: 33500 | K85: 4.3 | L85: 3 | M85: 22 | O85: No | P85: UC-0068
A86: UC-0084 | B86: Seun Price | C86: Strategy | D86: Junior | E86: Manchester | F86: Hybrid | G86: Male | H86: 24 | I86: 0.3 | J86: 39000 | K86: 6.9 | L86: 4 | M86: 43 | O86: No | P86: UC-0068
A87: UC-0085 | B87: Chris Vasquez | C87: Strategy | D87: Junior | E87: London | F87: Hybrid | G87: Male | H87: 23 | I87: 1.6 | J87: 37000 | K87: 3.7 | L87: 3 | M87: 28 | O87: Yes | P87: UC-0068
A88: UC-0086 | B88: Michael Nduka | C88: Strategy | D88: Junior | E88: London | F88: Office | G88: Male | H88: 25 | I88: 1.5 | J88: 37500 | K88: 5.4 | L88: 3 | M88: 26 | O88: No | P88: UC-0068
A89: UC-0087 | B89: Cian Moretti | C89: Strategy | D89: Junior | E89: Manchester | F89: Remote | G89: Male | H89: 22 | I89: 0.6 | J89: 36000 | K89: 3.5 | L89: 3 | M89: 18 | O89: No | P89: UC-0068
A90: UC-0088 | B90: Nathan Vargas | C90: Strategy | D90: Junior | E90: Manchester | F90: Remote | G90: Male | H90: 26 | I90: 1.5 | J90: 39000 | K90: 5.3 | L90: 4 | M90: 41 | O90: No | P90: UC-0068
A91: UC-0089 | B91: Saoirse Onyekachi | C91: Strategy | D91: Junior | E91: Edinburgh | F91: Office | G91: Female | H91: 29 | I91: 1.4 | J91: 33500 | K91: 5.1 | L91: 3 | M91: 32 | O91: No | P91: UC-0068
A92: UC-0090 | B92: Elliot Novak | C92: Strategy | D92: Junior | E92: Edinburgh | F92: Hybrid | G92: Male | H92: 26 | I92: 0.6 | J92: 39000 | K92: 6.2 | L92: 4 | M92: 32 | O92: Yes | P92: UC-0068
A93: UC-0091 | B93: David Varga | C93: Finance | D93: Director | E93: London | F93: Hybrid | G93: Male | H93: 53 | I93: 10 | J93: 145500 | K93: 19.5 | L93: 3 | M93: 13 | N93: 2023 | O93: No | P93: UC-0000
A94: UC-0092 | B94: Priya Turner | C94: Finance | D94: Lead | E94: London | F94: Hybrid | G94: Female | H94: 46 | I94: 2.3 | J94: 101000 | K94: 17.9 | L94: 4 | M94: 9 | N94: 2023 | O94: Yes | P94: UC-0091
A95: UC-0093 | B95: Sunita Tessema | C95: Finance | D95: Lead | E95: London | F95: Hybrid | G95: Female | H95: 42 | I95: 7.3 | J95: 103000 | K95: 19.2 | L95: 4 | M95: 26 | N95: 2020 | O95: No | P95: UC-0091
A96: UC-0094 | B96: Frankie Lawton | C96: Finance | D96: Lead | E96: Manchester | F96: Hybrid | G96: Non-binary | H96: 41 | I96: 6.6 | J96: 99000 | K96: 17.6 | L96: 3 | M96: 12 | N96: 2022 | O96: No | P96: UC-0091
A97: UC-0095 | B97: Hana Sato | C97: Finance | D97: Lead | E97: London | F97: Hybrid | G97: Female | H97: 40 | I97: 8.4 | J97: 97000 | K97: 16.2 | L97: 3 | M97: 6 | N97: 2024 | O97: No | P97: UC-0091
A98: UC-0096 | B98: Iain Onyekachi | C98: Finance | D98: Senior | E98: Manchester | F98: Hybrid | G98: Male | H98: 36 | I98: 8.1 | J98: 85500 | K98: 14.4 | L98: 3 | M98: 25 | N98: 2023 | O98: No | P98: UC-0092
A99: UC-0097 | B99: Amara Ferreira | C99: Finance | D99: Senior | E99: London | F99: Remote | G99: Female | H99: 35 | I99: 8.3 | J99: 76500 | K99: 14.1 | L99: 3 | M99: 27 | N99: 2023 | O99: No | P99: UC-0092
A100: UC-0098 | B100: Niall Foster | C100: Finance | D100: Senior | E100: London | F100: Remote | G100: Male | H100: 32 | I100: 4.3 | J100: 77500 | K100: 12.3 | L100: 3 | M100: 19 | N100: 2022 | O100: No | P100: UC-0092
A101: UC-0099 | B101: Renata Leblanc | C101: Finance | D101: Senior | E101: London | F101: Hybrid | G101: Female | H101: 33 | I101: 7.4 | J101: 72000 | K101: 11 | L101: 3 | M101: 22 | N101: 2024 | O101: No | P101: UC-0092
A102: UC-0100 | B102: James Ojo | C102: Finance | D102: Senior | E102: Manchester | F102: Hybrid | G102: Male | H102: 30 | I102: 7.1 | J102: 81500 | K102: 10.4 | L102: 3 | M102: 9 | N102: 2020 | O102: No | P102: UC-0092
A103: UC-0101 | B103: Blessing Diallo | C103: Finance | D103: Senior | E103: London | F103: Remote | G103: Female | H103: 45 | I103: 5.3 | J103: 82000 | K103: 14.6 | L103: 4 | M103: 30 | N103: 2022 | O103: No | P103: UC-0092
A104: UC-0102 | B104: Darius Balogun | C104: Finance | D104: Senior | E104: London | F104: Remote | G104: Male | H104: 38 | I104: 4.2 | J104: 78000 | K104: 10.8 | L104: 3 | M104: 15 | N104: 2023 | O104: No | P104: UC-0092
... A118: UC-0116 | B118: Elliot Reynolds | C118: Finance | D118: Mid | E118: Manchester | F118: Hybrid | G118: Male | H118: 32 | I118: 4.4 | J118: 55000 | K118: 7.3 | L118: 3 | M118: 26 | N118: 2023 | O118: No | P118: UC-0096
A119: UC-0117 | B119: Nnamdi Kapoor | C119: Finance | D119: Mid | E119: London | F119: Office | G119: Male | H119: 32 | I119: 0.3 | J119: 54000 | K119: 12.2 | L119: 4 | M119: 40 | O119: No | P119: UC-0096
A120: UC-0118 | B120: Oliver Patterson | C120: Finance | D120: Mid | E120: London | F120: Remote | G120: Male | H120: 34 | I120: 5.7 | J120: 60000 | K120: 8.8 | L120: 4 | M120: 34 | N120: 2023 | O120: Yes | P120: UC-0096
A121: UC-0119 | B121: Adaora Lawton | C121: Finance | D121: Junior | E121: Manchester | F121: Office | G121: Female | H121: 24 | I121: 0.3 | J121: 37500 | K121: 9.8 | L121: 5 | M121: 32 | O121: No | P121: UC-0105
A122: UC-0120 | B122: David McCarthy | C122: Finance | D122: Junior | E122: Manchester | F122: Office | G122: Male | H122: 23 | I122: 0.9 | J122: 41500 | K122: 6.1 | L122: 5 | M122: 45 | O122: Yes | P122: UC-0105
A123: UC-0121 | B123: Imogen Asante | C123: Finance | D123: Junior | E123: London | F123: Hybrid | G123: Female | H123: 22 | I123: 0.3 | J123: 32000 | K123: 4.6 | L123: 3 | M123: 31 | O123: No | P123: UC-0105
A124: UC-0122 | B124: Bart Mehta | C124: Finance | D124: Junior | E124: Edinburgh | F124: Remote | G124: Male | H124: 26 | I124: 0.8 | J124: 31500 | K124: 2.7 | L124: 2 | M124: 15 | O124: No | P124: UC-0105
A125: UC-0123 | B125: Femi Santos | C125: Finance | D125: Junior | E125: Edinburgh | F125: Hybrid | G125: Female | H125: 25 | I125: 1.4 | J125: 33500 | K125: 2.7 | L125: 3 | M125: 34 | O125: No | P125: UC-0105
A126: UC-0124 | B126: Abdou Nduka | C126: Finance | D126: Junior | E126: London | F126: Remote | G126: Male | H126: 22 | I126: 1.1 | J126: 36500 | K126: 4.3 | L126: 3 | M126: 23 | O126: No | P126: UC-0105
A127: UC-0125 | B127: Xavier Vestergaard | C127: Finance | D127: Junior | E127: London | F127: Office | G127: Male | H127: 27 | I127: 0.3 | J127: 33500 | K127: 5.2 | L127: 3 | M127: 30 | O127: No | P127: UC-0105
A128: UC-0126 | B128: Wanjiku Tessema | C128: Finance | D128: Junior | E128: London | F128: Remote | G128: Female | H128: 28 | I128: 0.5 | J128: 33000 | K128: 5.8 | L128: 3 | M128: 37 | O128: No | P128: UC-0105
A129: UC-0127 | B129: Brendan Baptiste | C129: Finance | D129: Junior | E129: London | F129: Hybrid | G129: Male | H129: 23 | I129: 1 | J129: 34500 | K129: 6.4 | L129: 3 | M129: 27 | O129: No | P129: UC-0105
A130: UC-0128 | B130: Tadhg Dubois | C130: Finance | D130: Junior | E130: London | F130: Remote | G130: Male | H130: 24 | I130: 0.7 | J130: 35500 | K130: 4 | L130: 3 | M130: 30 | O130: No | P130: UC-0105
A131: UC-0129 | B131: George Novak | C131: Operations | D131: Director | E131: London | F131: Hybrid | G131: Male | H131: 42 | I131: 12.7 | J131: 126000 | K131: 16.3 | L131: 2 | M131: 8 | N131: 2020 | O131: No | P131: UC-0000
A132: UC-0130 | B132: Pooja Kowalski | C132: Operations | D132: Lead | E132: Manchester | F132: Hybrid | G132: Female | H132: 42 | I132: 8.5 | J132: 96000 | K132: 15.2 | L132: 4 | M132: 17 | N132: 2023 | O132: No | P132: UC-0129
A133: UC-0131 | B133: Obinna Holloway | C133: Operations | D133: Lead | E133: Edinburgh | F133: Hybrid | G133: Male | H133: 42 | I133: 10.9 | J133: 107500 | K133: 18.6 | L133: 4 | M133: 29 | N133: 2023 | O133: No | P133: UC-0129
A134: UC-0132 | B134: Kofi Hassan | C134: Operations | D134: Lead | E134: London | F134: Office | G134: Male | H134: 34 | I134: 9.8 | J134: 111500 | K134: 20.2 | L134: 5 | M134: 27 | N134: 2024 | O134: No | P134: UC-0129
A135: UC-0133 | B135: Callum Patel | C135: Operations | D135: Senior | E135: London | F135: Remote | G135: Male | H135: 31 | I135: 7.1 | J135: 87000 | K135: 13.5 | L135: 4 | M135: 8 | N135: 2022 | O135: No | P135: UC-0130
A136: UC-0134 | B136: Emre Ferreira | C136: Operations | D136: Senior | E136: Manchester | F136: Hybrid | G136: Male | H136: 34 | I136: 4.9 | J136: 78500 | K136: 12.7 | L136: 4 | M136: 7 | N136: 2022 | O136: No | P136: UC-0130
A137: UC-0135 | B137: Raphael Okonkwo | C137: Operations | D137: Senior | E137: London | F137: Hybrid | G137: Male | H137: 31 | I137: 7.1 | J137: 66500 | K137: 10.5 | L137: 2 | M137: 16 | N137: 2022 | O137: No | P137: UC-0130
A138: UC-0136 | B138: Soren Nair | C138: Operations | D138: Senior | E138: London | F138: Hybrid | G138: Male | H138: 27 | I138: 6.8 | J138: 73000 | K138: 14.3 | L138: 3 | M138: 24 | N138: 2024 | O138: No | P138: UC-0130
A139: UC-0137 | B139: Saskia Al-Hassan | C139: Operations | D139: Senior | E139: Manchester | F139: Hybrid | G139: Female | H139: 33 | I139: 4.5 | J139: 75500 | K139: 14.3 | L139: 4 | M139: 35 | N139: 2022 | O139: No | P139: UC-0130
A140: UC-0138 | B140: Daniel Das | C140: Operations | D140: Senior | E140: Edinburgh | F140: Remote | G140: Male | H140: 34 | I140: 6.6 | J140: 84000 | K140: 14.8 | L140: 4 | M140: 27 | N140: 2020 | O140: No | P140: UC-0130
A141: UC-0139 | B141: Ravi Clarke | C141: Operations | D141: Senior | E141: Manchester | F141: Remote | G141: Male | H141: 33 | I141: 5.4 | J141: 80500 | K141: 10.4 | L141: 4 | M141: 18 | N141: 2021 | O141: No | P141: UC-0130
A142: UC-0140 | B142: Fiona Varga | C142: Operations | D142: Senior | E142: London | F142: Remote | G142: Female | H142: 38 | I142: 6 | J142: 68500 | K142: 12.3 | L142: 3 | M142: 22 | N142: 2023 | O142: No | P142: UC-0130
... A161: UC-0159 | B161: Will Sato | C161: Operations | D161: Mid | E161: Manchester | F161: Remote | G161: Male | H161: 25 | I161: 4.1 | J161: 51000 | K161: 6.6 | L161: 3 | M161: 19 | N161: 2024 | O161: No | P161: UC-0133
A162: UC-0160 | B162: Andrei Nduka | C162: Operations | D162: Junior | E162: Manchester | F162: Office | G162: Male | H162: 24 | I162: 0.8 | J162: 35500 | K162: 7.1 | L162: 4 | M162: 33 | O162: No | P162: UC-0143
A163: UC-0161 | B163: Tom Finlay | C163: Operations | D163: Junior | E163: London | F163: Remote | G163: Male | H163: 28 | I163: 1.6 | J163: 34000 | K163: 5.7 | L163: 3 | M163: 27 | O163: No | P163: UC-0143
A164: UC-0162 | B164: George Reyes | C164: Operations | D164: Junior | E164: London | F164: Hybrid | G164: Male | H164: 25 | I164: 2.8 | J164: 34500 | K164: 6.1 | L164: 3 | M164: 21 | O164: No | P164: UC-0143
A165: UC-0163 | B165: Henrik Holloway | C165: Operations | D165: Junior | E165: London | F165: Hybrid | G165: Male | H165: 28 | I165: 1.7 | J165: 33000 | K165: 4.2 | L165: 3 | M165: 21 | O165: No | P165: UC-0143
A166: UC-0164 | B166: George Pierce | C166: Operations | D166: Junior | E166: London | F166: Office | G166: Male | H166: 22 | I166: 0.3 | J166: 35000 | K166: 3.5 | L166: 4 | M166: 34 | O166: Yes | P166: UC-0143
A167: UC-0165 | B167: Patrick Tanaka | C167: Operations | D167: Junior | E167: London | F167: Office | G167: Male | H167: 27 | I167: 1.4 | J167: 33000 | K167: 5.4 | L167: 3 | M167: 29 | O167: No | P167: UC-0143
A168: UC-0166 | B168: Amara Kowalski | C168: Operations | D168: Junior | E168: London | F168: Hybrid | G168: Female | H168: 22 | I168: 2.5 | J168: 35000 | K168: 7.6 | L168: 4 | M168: 32 | O168: No | P168: UC-0143
A169: UC-0167 | B169: Priya Sato | C169: Operations | D169: Junior | E169: London | F169: Hybrid | G169: Female | H169: 22 | I169: 1.5 | J169: 25000 | K169: 2.3 | L169: 1 | M169: 27 | O169: No | P169: UC-0143
A170: UC-0168 | B170: Morgan Bennett | C170: Operations | D170: Junior | E170: London | F170: Hybrid | G170: Non-binary | H170: 22 | I170: 1.7 | J170: 32000 | K170: 5.1 | L170: 3 | M170: 21 | O170: No | P170: UC-0143
A171: UC-0169 | B171: Sarah Fraser | C171: Operations | D171: Junior | E171: Manchester | F171: Hybrid | G171: Female | H171: 24 | I171: 1.2 | J171: 30000 | K171: 4.5 | L171: 3 | M171: 28 | O171: No | P171: UC-0143
A172: UC-0170 | B172: Theo Asante | C172: Operations | D172: Junior | E172: London | F172: Office | G172: Male | H172: 22 | I172: 1.3 | J172: 34000 | K172: 4.5 | L172: 3 | M172: 34 | O172: No | P172: UC-0143
A173: UC-0171 | B173: Imogen Bennett | C173: Operations | D173: Junior | E173: Manchester | F173: Office | G173: Female | H173: 27 | I173: 1.2 | J173: 31000 | K173: 5.9 | L173: 3 | M173: 24 | O173: No | P173: UC-0143
...

Sheet Ch3 — Counting
A1: Chapter 3 — Counting & Headcount
A2: Formulas reference the 'Employee Data' sheet in this workbook.
A4: COUNT FAMILY
A5: Total employees (COUNTA) | B5: =COUNTA('Employee Data'!B3:B202) -> 200 | C5: → 200
A6: Employees with salary on record (COUNT) | B6: =COUNT('Employee Data'!J3:J202) -> 200 | C6: → 200 (data quality check)
A7: Employees never promoted (COUNTBLANK) | B7: =COUNTBLANK('Employee Data'!N3:N202) -> 59 | C7: → ~59 (Juniors too new + some Mids)
A9: COUNTIF — Single Condition
A10: Headcount: Technology | B10: =COUNTIF('Employee Data'!C3:C202,"Technology") -> 50
A11: Headcount: Strategy | B11: =COUNTIF('Employee Data'!C3:C202,"Strategy") -> 40
A12: Headcount: Finance | B12: =COUNTIF('Employee Data'!C3:C202,"Finance") -> 38
A13: Headcount: Operations | B13: =COUNTIF('Employee Data'!C3:C202,"Operations") -> 45
A14: Headcount: People & Culture | B14: =COUNTIF('Employee Data'!C3:C202,"People & Culture") -> 27
A15: Senior-level employees | B15: =COUNTIF('Employee Data'!D3:D202,"Senior") -> 45
A16: Remote workers | B16: =COUNTIF('Employee Data'!F3:F202,"Remote") -> 72
A17: Hybrid workers | B17: =COUNTIF('Employee Data'!F3:F202,"Hybrid") -> 87
A18: Employees rated 4 or above (>=4) | B18: =COUNTIF('Employee Data'!L3:L202,">=4") -> 81
A19: Voluntary leavers (total) | B19: =COUNTIF('Employee Data'!O3:O202,"Yes") -> 31
A21: COUNTIFS — Multiple Conditions
A22: Technology leavers | B22: =COUNTIFS('Employee Data'!C3:C202,"Technology",'Employee Data'!O3:O202,"Yes") -> 13 | C22: → 13 — the attrition story
A23: Female Senior employees | B23: =COUNTIFS('Employee Data'!G3:G202,"Female",'Employee Data'!D3:D202,"Senior") -> 16
A24: Male Leads in London | B24: =COUNTIFS('Employee Data'!G3:G202,"Male",'Employee Data'!D3:D202,"Lead",'Employee Data'!E3:E202,"London") -> 7
A25: High performers who left (≥4 AND leaver) | B25: =COUNTIFS('Employee Data'!L3:L202,">=4",'Employee Data'!O3:O202,"Yes") -> 24 | C25: → majority of leavers — alarming
A27: Try It Yourself — Answers
A28: Q1: Total headcount | B28: =COUNTA('Employee Data'!B3:B202) -> 200
A29: Q2: Missing salaries? | B29: =COUNTBLANK('Employee Data'!J3:J202) -> 0 | C29: → 0 (none missing)
A30: Q3: Office workers in Manchester | B30: =COUNTIFS('Employee Data'!E3:E202,"Manchester",'Employee Data'!F3:F202,"Office") -> 9
A31: Q4: Junior leavers | B31: =COUNTIFS('Employee Data'!D3:D202,"Junior",'Employee Data'!O3:O202,"Yes") -> 11
A32: Q5: Remote AND rated 5 | B32: =COUNTIFS('Employee Data'!F3:F202,"Remote",'Employee Data'!L3:L202,5) -> 10

Sheet Ch4 — Salary & Cost
A1: Chapter 4 — Salary Cost & SUMIF
A2: SUM, SUMIF, SUMIFS, SUMPRODUCT.
A4: TOTAL SALARY
A5: Total salary bill | B5: =SUM('Employee Data'!J3:J202) -> 12504000
A6: Total bonus cost | B6: =SUMPRODUCT('Employee Data'!J3:J202,'Employee Data'!K3:K202/100) -> 1472305 | C6: Multiply each salary × bonus%, sum all
A7: Total cash compensation | B7: =SUM('Employee Data'!J3:J202)+SUMPRODUCT('Employee Data'!J3:J202,'Employee Data'!K3:K202/100) -> 13976305
A8: Leavers' combined salary | B8: =SUMIF('Employee Data'!O3:O202,"Yes",'Employee Data'!J3:J202) -> 1908500 | C8: Cost-of-attrition starting point
A10: SUMIF — Department Salary Costs
A11: Total salary — Technology | B11: =SUMIF('Employee Data'!C3:C202,"Technology",'Employee Data'!J3:J202) -> 3586500
A12: Total salary — Strategy | B12: =SUMIF('Employee Data'!C3:C202,"Strategy",'Employee Data'!J3:J202) -> 2679000
A13: Total salary — Finance | B13: =SUMIF('Employee Data'!C3:C202,"Finance",'Employee Data'!J3:J202) -> 2365000
A14: Total salary — Operations | B14: =SUMIF('Employee Data'!C3:C202,"Operations",'Employee Data'!J3:J202) -> 2515000
A15: Total salary — People & Culture | B15: =SUMIF('Employee Data'!C3:C202,"People & Culture",'Employee Data'!J3:J202) -> 1358500
A17: SUMIF — Other Cuts
A18: Total salary — Senior level | B18: =SUMIF('Employee Data'!D3:D202,"Senior",'Employee Data'!J3:J202) -> 3671500
A19: Total salary — Remote workers | B19: =SUMIF('Employee Data'!F3:F202,"Remote",'Employee Data'!J3:J202) -> 4262500
A21: SUMIFS — Multiple Conditions
A22: Salary — Female Seniors | B22: =SUMIFS('Employee Data'!J3:J202,'Employee Data'!G3:G202,"Female",'Employee Data'!D3:D202,"Senior") -> 1256000
A23: Salary — Hybrid, Technology dept | B23: =SUMIFS('Employee Data'!J3:J202,'Employee Data'!F3:F202,"Hybrid",'Employee Data'!C3:C202,"Technology") -> 1636000
A24: Bonus cost — Performance ≥4 (SUMPRODUCT) | B24: =SUMPRODUCT(('Employee Data'!L3:L202>=4)*'Employee Data'!J3:J202*'Employee Data'!K3:K202/100) -> 733994 | C24: Array-style SUMPRODUCT — no helper column needed
A25: Tech leavers' total salary | B25: =SUMIFS('Employee Data'!J3:J202,'Employee Data'!C3:C202,"Technology",'Employee Data'!O3:O202,"Yes") -> 820000
A27: AVERAGE COST
A28: Average salary — all staff | B28: =AVERAGE('Employee Data'!J3:J202) -> 62520
A29: Average salary — Technology | B29: =AVERAGEIF('Employee Data'!C3:C202,"Technology",'Employee Data'!J3:J202) -> 71730
A30: Average salary — Operations | B30: =AVERAGEIF('Employee Data'!C3:C202,"Operations",'Employee Data'!J3:J202) -> 55888.889

Sheet Ch5 — Pay Equity
A1: Chapter 5 — Averages & Pay Equity
A2: Mean, Median, Mode — and the gender pay gap.
A4: MEAN, MEDIAN, MODE
A5: Mean salary | B5: =AVERAGE('Employee Data'!J3:J202) -> 62520
A6: Median salary | B6: =MEDIAN('Employee Data'!J3:J202) -> 54750 | C6: Compare: median lower due to high-earner skew
A7: Mean–Median gap | B7: =AVERAGE('Employee Data'!J3:J202)-MEDIAN('Employee Data'!J3:J202) -> 7770 | C7: Gap reveals right-skew from Directors
A8: Mean age | B8: =AVERAGE('Employee Data'!H3:H202) -> 30.535
A9: Mean tenure | B9: =AVERAGE('Employee Data'!I3:I202) -> 3.9555
A10: Most common performance rating (MODE) | B10: =MODE('Employee Data'!L3:L202) -> 3 | C10: → 3
A12: GENDER PAY GAP — OVERALL
A13: Mean salary — Female | B13: =AVERAGEIF('Employee Data'!G3:G202,"Female",'Employee Data'!J3:J202) -> 58555.556
A14: Mean salary — Male | B14: =AVERAGEIF('Employee Data'!G3:G202,"Male",'Employee Data'!J3:J202) -> 64119.469
A15: Mean gap % (M higher than F) | B15: =(AVERAGEIF('Employee Data'!G3:G202,"Male",'Employee Data'!J3:J202)-AVERAGEIF('Employee Data'!G3:G202,"Female",'Employee Data'!J3:J202))/AVERAGEIF('Employee Data'!G3:G202,"Male",'Employee Data'!J3:J202) -> 0.086774166 | C15: Format as % — ~8.7%
A17: GAP WITHIN JOB LEVELS (controls for level mix)
A18: Female mean salary — Junior | B18: =AVERAGEIFS('Employee Data'!J3:J202,'Employee Data'!G3:G202,"Female",'Employee Data'!D3:D202,"Junior") -> 32538.462
A19: Male mean salary — Junior | B19: =AVERAGEIFS('Employee Data'!J3:J202,'Employee Data'!G3:G202,"Male",'Employee Data'!D3:D202,"Junior") -> 36285.714
A20: Female mean salary — Mid | B20: =AVERAGEIFS('Employee Data'!J3:J202,'Employee Data'!G3:G202,"Female",'Employee Data'!D3:D202,"Mid") -> 50185.185
A21: Male mean salary — Mid | B21: =AVERAGEIFS('Employee Data'!J3:J202,'Employee Data'!G3:G202,"Male",'Employee Data'!D3:D202,"Mid") -> 54743.243
A22: Female mean salary — Senior | B22: =AVERAGEIFS('Employee Data'!J3:J202,'Employee Data'!G3:G202,"Female",'Employee Data'!D3:D202,"Senior") -> 78500
A23: Male mean salary — Senior | B23: =AVERAGEIFS('Employee Data'!J3:J202,'Employee Data'!G3:G202,"Male",'Employee Data'!D3:D202,"Senior") -> 83125
A24: Female mean salary — Lead | B24: =AVERAGEIFS('Employee Data'!J3:J202,'Employee Data'!G3:G202,"Female",'Employee Data'!D3:D202,"Lead") -> 100250
A25: Male mean salary — Lead | B25: =AVERAGEIFS('Employee Data'!J3:J202,'Employee Data'!G3:G202,"Male",'Employee Data'!D3:D202,"Lead") -> 115000
A26: Female mean salary — Director | B26: =AVERAGEIFS('Employee Data'!J3:J202,'Employee Data'!G3:G202,"Female",'Employee Data'!D3:D202,"Director") -> 141750
A27: Male mean salary — Director | B27: =AVERAGEIFS('Employee Data'!J3:J202,'Employee Data'!G3:G202,"Male",'Employee Data'!D3:D202,"Director") -> 140500

Sheet Ch6 — Spread & Outliers
A1: Chapter 6 — Spread & Outliers
A2: MIN, MAX, STDEV — identifying unusual values.
A4: RANGE & STANDARD DEVIATION
A5: Minimum salary | B5: =MIN('Employee Data'!J3:J202) -> 25000
A6: Maximum salary | B6: =MAX('Employee Data'!J3:J202) -> 149500
A7: Salary range (max–min) | B7: =MAX('Employee Data'!J3:J202)-MIN('Employee Data'!J3:J202) -> 124500
A8: Standard deviation of salary | B8: =STDEV('Employee Data'!J3:J202) -> 28818.216 | C8: Spread around the mean
A9: Coefficient of variation | B9: =STDEV('Employee Data'!J3:J202)/AVERAGE('Employee Data'!J3:J202) -> 0.46094395 | C9: Format as % — relative spread
A11: OUTLIER DETECTION (2-StDev rule)
A12: Upper outlier threshold (Mean+2×StDev) | B12: =AVERAGE('Employee Data'!J3:J202)+2*STDEV('Employee Data'!J3:J202) -> 120156.43
A13: Lower outlier threshold (Mean–2×StDev) | B13: =AVERAGE('Employee Data'!J3:J202)-2*STDEV('Employee Data'!J3:J202) -> 4883.5689
A14: Count of employees above upper threshold | B14: =COUNTIF('Employee Data'!J3:J202,">"&(AVERAGE('Employee Data'!J3:J202)+2*STDEV('Employee Data'!J3:J202))) -> 10
A16: SPREAD BY DEPARTMENT (array formulas)
A17: Salary StDev — Technology | B17: =STDEV(IF('Employee Data'!C3:C202="Technology",'Employee Data'!J3:J202)) -> 28818.216 | C17: Ctrl+Shift+Enter in older Excel (array formula)
A18: Salary StDev — Strategy | B18: =IFERROR(STDEV(IF('Employee Data'!C3:C202="Strategy",'Employee Data'!J3:J202)),"—") -> — | C18: Ctrl+Shift+Enter in older Excel (array formula)
A19: Salary StDev — Finance | B19: =IFERROR(STDEV(IF('Employee Data'!C3:C202="Finance",'Employee Data'!J3:J202)),"—") -> — | C19: Ctrl+Shift+Enter in older Excel (array formula)
A20: Salary StDev — Operations | B20: =IFERROR(STDEV(IF('Employee Data'!C3:C202="Operations",'Employee Data'!J3:J202)),"—") -> — | C20: Ctrl+Shift+Enter in older Excel (array formula)
A21: Salary StDev — People & Culture | B21: =IFERROR(STDEV(IF('Employee Data'!C3:C202="People & Culture",'Employee Data'!J3:J202)),"—") -> — | C21: Ctrl+Shift+Enter in older Excel (array formula)

Sheet Ch7 — Attrition
A1: Chapter 7 — Attrition Analysis
A2: Rates, profiles, and the cost of losing people.
A4: ATTRITION RATES
A5: Overall attrition rate | B5: =COUNTIF('Employee Data'!O3:O202,"Yes")/COUNTA('Employee Data'!B3:B202) -> 0.155 | C5: Format as % — ~15.5%
A6: Attrition rate — Technology | B6: =COUNTIFS('Employee Data'!C3:C202,"Technology",'Employee Data'!O3:O202,"Yes")/COUNTIF('Employee Data'!C3:C202,"Technology") -> 0.26 | C6: Format as % ← HIGHEST — nearly double average
A7: Attrition rate — Strategy | B7: =COUNTIFS('Employee Data'!C3:C202,"Strategy",'Employee Data'!O3:O202,"Yes")/COUNTIF('Employee Data'!C3:C202,"Strategy") -> 0.15 | C7: Format as %
A8: Attrition rate — Finance | B8: =COUNTIFS('Employee Data'!C3:C202,"Finance",'Employee Data'!O3:O202,"Yes")/COUNTIF('Employee Data'!C3:C202,"Finance") -> 0.13157895 | C8: Format as %
A9: Attrition rate — Operations | B9: =COUNTIFS('Employee Data'!C3:C202,"Operations",'Employee Data'!O3:O202,"Yes")/COUNTIF('Employee Data'!C3:C202,"Operations") -> 0.066666667 | C9: Format as % ← LOWEST — stable workforce
A10: Attrition rate — People & Culture | B10: =COUNTIFS('Employee Data'!C3:C202,"People & Culture",'Employee Data'!O3:O202,"Yes")/COUNTIF('Employee Data'!C3:C202,"People & Culture") -> 0.14814815 | C10: Format as %
A12: LEAVER vs STAYER PROFILE
A13: Leaver avg performance | B13: =AVERAGEIF('Employee Data'!O3:O202,"Yes",'Employee Data'!L3:L202) -> 4 | C13: → ~4.00 — losing HIGH performers
A14: Stayer avg performance | B14: =AVERAGEIF('Employee Data'!O3:O202,"No",'Employee Data'!L3:L202) -> 3.2485207 | C14: → ~3.25 — gap is the alarm signal
A15: Leaver avg tenure | B15: =AVERAGEIF('Employee Data'!O3:O202,"Yes",'Employee Data'!I3:I202) -> 3.5
A16: Tech leaver avg performance | B16: =AVERAGEIFS('Employee Data'!L3:L202,'Employee Data'!C3:C202,"Technology",'Employee Data'!O3:O202,"Yes") -> 4
A17: High performers (≥4) who left | B17: =COUNTIFS('Employee Data'!L3:L202,">=4",'Employee Data'!O3:O202,"Yes") -> 24
A19: COST OF ATTRITION
A20: Leavers' combined salary | B20: =SUMIF('Employee Data'!O3:O202,"Yes",'Employee Data'!J3:J202) -> 1908500
A21: Conservative replacement cost (×50%) | B21: =SUMIF('Employee Data'!O3:O202,"Yes",'Employee Data'!J3:J202)*0.5 -> 954250
A22: High-end replacement cost (×200%) | B22: =SUMIF('Employee Data'!O3:O202,"Yes",'Employee Data'!J3:J202)*2 -> 3817000

Sheet Ch7b — Correlations
A1: Chapter 7 — Correlation Analysis
A2: CORREL — relationships between workforce variables.
A4: CORREL FORMULAS
A5: Tenure vs Salary (overall) | B5: =CORREL('Employee Data'!I3:I202,'Employee Data'!J3:J202) -> 0.86255692 | C5: ~0.86 — strong, but see confounding note below
A6: Performance vs Salary (unconditional) | B6: =CORREL('Employee Data'!L3:L202,'Employee Data'!J3:J202) -> 0.26709813 | C6: ~0.27 — suppressed by level effect
A7: Training Hours vs Performance | B7: =CORREL('Employee Data'!M3:M202,'Employee Data'!L3:L202) -> 0.31332228 | C7: ~0.31 — weak-moderate; not causal
A8: Age vs Salary | B8: =CORREL('Employee Data'!H3:H202,'Employee Data'!J3:J202) -> 0.84163031
A10: WITHIN-LEVEL CORRELATIONS (array formulas, Ctrl+Shift+Enter)
A11: Tenure vs Salary — Senior only | B11: =CORREL(IF('Employee Data'!D3:D202="Senior",'Employee Data'!I3:I202),IF('Employee Data'!D3:D202="Senior",'Employee Data'!J3:J202)) -> 0.44482113 | C11: ~0.40 — much weaker than overall; the true within-level signal
A12: Perf vs Salary — Senior only | B12: =CORREL(IF('Employee Data'!D3:D202="Senior",'Employee Data'!L3:L202),IF('Employee Data'!D3:D202="Senior",'Employee Data'!J3:J202)) -> 0.61345821 | C12: ~0.61 — stronger; within level, performance matters more than across all levels
A14: INTERPRETATION GUIDE
A15: Coefficient Range | B15: Interpretation | C15: Unreal Consulting Example
A16: 0.80–1.00 | B16: Very strong positive | C16: Tenure–Salary overall (0.86) — confounded by level
A17: 0.50–0.79 | B17: Moderate–Strong | C17: Perf–Salary within levels (0.61–0.79)
A18: 0.30–0.49 | B18: Moderate | C18: Training–Performance (0.31)
A19: 0.10–0.29 | B19: Weak–Moderate | C19: Perf–Salary unconditional (0.27)
A20: -0.10–0.10 | B20: Negligible | C20: No meaningful linear relationship

Sheet Ch9 — Pivot Reference
A1: Chapter 9 — Expected Pivot Table Outputs
A2: Reference: what your Pivot Tables should show.
A4: Headcount & Attrition by Department
A5: Department | B5: Headcount | C5: Leavers | D5: Attrition % | E5: Note
A6: Technology | B6: 50 | C6: 13 | D6: 26.0% | E6: ← Highest — nearly double average
A7: Strategy | B7: 40 | C7: 6 | D7: 15.0%
A8: Finance | B8: 38 | C8: 5 | D8: 13.2%
A9: Operations | B9: 45 | C9: 3 | D9: 6.7% | E9: ← Lowest — stable workforce
A10: People & Culture | B10: 27 | C10: 4 | D10: 14.8%
A11: TOTAL | B11: 200 | C11: 31 | D11: 15.5% | E11: Overall company attrition
A14: Average Salary by Level & Gender (what your Pivot should show)
A15: Job Level | B15: Female | C15: Male | D15: Gap % | E15: Director note
A16: Junior | B16: £32,538 | C16: £36,286 | D16: 10.3%
A17: Mid | B17: £50,185 | C17: £54,743 | D17: 8.3%
A18: Senior | B18: £78,500 | C18: £83,125 | D18: 5.6%
A19: Lead | B19: £100,250 | C19: £115,000 | D19: 12.8% | E19: Small n (10F, 8M) — caveat
A20: Director | B20: — | C20: £139,500 | D20: n/a | E20: No female Directors in Finance or Operations — flag for HR
